ic_parent_api_btk/__init__.py
ic_parent_api_btk/base.py
ic_parent_api_btk/ic_api_client.py
ic_parent_api_btk/infinitecampus.py
ic_parent_api_btk/errors/__init__.py
ic_parent_api_btk/errors/ic_error.py
ic_parent_api_btk/models/__init__.py
ic_parent_api_btk/models/assignment.py
ic_parent_api_btk/models/base.py
ic_parent_api_btk/models/course.py
ic_parent_api_btk/models/enrollment.py
ic_parent_api_btk/models/grade.py
ic_parent_api_btk/models/gradingtask.py
ic_parent_api_btk/models/placement.py
ic_parent_api_btk/models/scheduleday.py
ic_parent_api_btk/models/student.py
ic_parent_api_btk/models/term.py
ic_parent_api_btk-0.0.19.dist-info/LICENSE
ic_parent_api_btk-0.0.19.dist-info/METADATA
ic_parent_api_btk-0.0.19.dist-info/WHEEL
ic_parent_api_btk-0.0.19.dist-info/top_level.txt
ic_parent_api_btk-0.0.19.dist-info/RECORD
