Metadata-Version: 2.1
Name: ic_parent_api_btk
Version: 0.0.19
Summary: A small async API wrapper for Infinite Campus Parents.
Home-page: https://github.com/bkeifer/ic_parent_api_btk
Author: Brian Keifer
Author-email: Jacob Schwartz <jake@schwartzpub.com>, Brian Keifer <brian@valinor.net>
License: Copyright (c) 2018 The Python Packaging Authority
Project-URL: Homepage, https://github.com/schwartzpub/ic_parent_api
Project-URL: Bug Tracker, https://github.com/schwartzpub/ic_parent_api/issues
Classifier: Programming Language :: Python :: 3
Classifier: License :: OSI Approved :: MIT License
Classifier: Operating System :: OS Independent
Requires-Python: >=3.9
License-File: LICENSE
Requires-Dist: aiohttp
Requires-Dist: pydantic<1.12.16,>=1.8.2
